staticclasses/__init__.py
staticclasses/core/__init__.py
staticclasses/tests/__init__.py
staticclasses/tests/test_try.py
staticclasses-1.0.1.dist-info/licenses/LICENSE.txt
staticclasses-1.0.1.dist-info/METADATA
staticclasses-1.0.1.dist-info/WHEEL
staticclasses-1.0.1.dist-info/top_level.txt
staticclasses-1.0.1.dist-info/RECORD
