Metadata-Version: 2.4
Name: staticclasses
Version: 1.0.1
Summary: This project allows for creating static classes in python.
Author-email: Johannes <johannes-programming@mailfence.com>
License: The MIT License (MIT)
Project-URL: Download, https://pypi.org/project/staticclasses/#files
Project-URL: Index, https://pypi.org/project/staticclasses/
Project-URL: Source, https://github.com/johannes-programming/staticclasses/
Project-URL: Website, https://staticclasses.johannes-programming.online/
Classifier: Development Status :: 5 - Production/Stable
Classifier: Intended Audience :: Developers
Classifier: License :: OSI Approved :: MIT License
Classifier: Natural Language :: English
Classifier: Operating System :: OS Independent
Classifier: Programming Language :: Python
Classifier: Programming Language :: Python :: 3
Classifier: Programming Language :: Python :: 3 :: Only
Classifier: Typing :: Typed
Requires-Python: >=3.11
License-File: LICENSE.txt
Dynamic: license-file
